topsis_tatvam_102303484/__init__.py
topsis_tatvam_102303484/topsis.py
topsis_tatvam_102303484-1.0.5.dist-info/METADATA
topsis_tatvam_102303484-1.0.5.dist-info/WHEEL
topsis_tatvam_102303484-1.0.5.dist-info/entry_points.txt
topsis_tatvam_102303484-1.0.5.dist-info/top_level.txt
topsis_tatvam_102303484-1.0.5.dist-info/RECORD
