Metadata-Version: 2.4
Name: topsis-tatvam-102303484
Version: 1.0.5
Summary: A Python package for TOPSIS (Technique for Order of Preference by Similarity to Ideal Solution) analysis
Home-page: https://github.com/tatvamjain/topsis-102303484
Author: Tatvam Jain
Author-email: tjain_be23@thapar.edu
Classifier: Programming Language :: Python :: 3
Classifier: License :: OSI Approved :: MIT License
Classifier: Operating System :: OS Independent
Requires-Python: >=3.6
Requires-Dist: pandas>=1.0.0
Requires-Dist: numpy>=1.18.0
Dynamic: author
Dynamic: author-email
Dynamic: classifier
Dynamic: description
Dynamic: description-content-type
Dynamic: home-page
Dynamic: requires-dist
Dynamic: requires-python
Dynamic: summary
